simple_slurm_command/__init__.py
simple_slurm_command/arguments.txt
simple_slurm_command/core.py
simple_slurm_command/filename_patterns.txt
simple_slurm_command/output_env_vars.txt
simple_slurm_command-0.2.3.dist-info/LICENSE
simple_slurm_command-0.2.3.dist-info/METADATA
simple_slurm_command-0.2.3.dist-info/WHEEL
simple_slurm_command-0.2.3.dist-info/top_level.txt
simple_slurm_command-0.2.3.dist-info/RECORD
