Metadata-Version: 2.1
Name: simple-slurm-command
Version: 0.2.3
Summary: A simple Python module to generate Slurm commands built on top of https://github.com/amq92/simple_slurm.
Home-page: https://github.com/takuma-yoneda/simple_slurm_command
Author: Takuma Yoneda
License: GNU Affero General Public License v3
Platform: UNKNOWN
Classifier: Programming Language :: Python :: 3
Classifier: License :: OSI Approved :: GNU Affero General Public License v3
Classifier: Operating System :: OS Independent
Requires-Python: >=3.6
License-File: LICENSE
